vplotlib/__init__.py
vplotlib/label.py
vplotlib-0.2.dist-info/licenses/LICENSE
vplotlib-0.2.dist-info/METADATA
vplotlib-0.2.dist-info/WHEEL
vplotlib-0.2.dist-info/top_level.txt
vplotlib-0.2.dist-info/RECORD
