Metadata-Version: 2.4
Name: vplotlib
Version: 0.2
Summary: A simple matplotlib wrapper for setting title and labels in one line
Author: Vishwa shah
Author-email: vishwashah686@gmail.com
License: MIT
License-File: LICENSE
Requires-Dist: matplotlib
Dynamic: author
Dynamic: author-email
Dynamic: license
Dynamic: license-file
Dynamic: requires-dist
Dynamic: summary
